budget_optimizer/__init__.py
budget_optimizer/_modidx.py
budget_optimizer/optimizer.py
budget_optimizer/utils/__init__.py
budget_optimizer/utils/model_classes.py
budget_optimizer/utils/model_helpers.py
budget_optimizer/utils/search_space_helper.py
budget_optimizer-0.1.1.dist-info/LICENSE
budget_optimizer-0.1.1.dist-info/METADATA
budget_optimizer-0.1.1.dist-info/WHEEL
budget_optimizer-0.1.1.dist-info/entry_points.txt
budget_optimizer-0.1.1.dist-info/top_level.txt
budget_optimizer-0.1.1.dist-info/RECORD
