Metadata-Version: 2.1
Name: budget_optimizer
Version: 0.1.1
Summary: Budget optimizer for nested MMMs
Home-page: https://github.com/redam94/budget_optimizer
Author: Matthew Reda
Author-email: m.reda94@gmail.com
License: Apache Software License 2.0
Keywords: mmm marketing budget optimizer kpi nested
Classifier: Development Status :: 4 - Beta
Classifier: Intended Audience :: Developers
Classifier: Natural Language :: English
Classifier: Programming Language :: Python :: 3.10
Classifier: Programming Language :: Python :: 3.11
Classifier: Programming Language :: Python :: 3.12
Classifier: License :: OSI Approved :: Apache Software License
Requires-Python: >=3.10
License-File: LICENSE
Requires-Dist: fastcore
Requires-Dist: pandas
Requires-Dist: numpy
Requires-Dist: pyswarms
Requires-Dist: scipy
Requires-Dist: xarray
Requires-Dist: matplotlib
Requires-Dist: seaborn
Requires-Dist: pyyaml
Requires-Dist: optuna
Provides-Extra: dev
